amap_mcp_server/__init__.py
amap_mcp_server/__main__.py
amap_mcp_server/_version.py
amap_mcp_server/server.py
amap_mcp_server-0.1.11.dist-info/METADATA
amap_mcp_server-0.1.11.dist-info/WHEEL
amap_mcp_server-0.1.11.dist-info/entry_points.txt
amap_mcp_server-0.1.11.dist-info/licenses/LICENSE
amap_mcp_server-0.1.11.dist-info/RECORD
