Metadata-Version: 2.4
Name: amap-mcp-server
Version: 0.1.11
Summary: Python版本高德地图MCP Server
Project-URL: Homepage, https://github.com/sugarforever/amap-mcp-server
Project-URL: Bug Tracker, https://github.com/sugarforever/amap-mcp-server/issues
License-File: LICENSE
Classifier: License :: OSI Approved :: MIT License
Classifier: Operating System :: OS Independent
Classifier: Programming Language :: Python :: 3
Requires-Python: >=3.10
Requires-Dist: mcp==1.8.1
Requires-Dist: requests>=2.32.3
